[
 {
  "table":"SRVDSRC",
  "data":
  [
   {
    "SRVDNAME":"ZSD_NFT_T008",
    "VERSION":"A",
    "CHANGED_BY":"SAP_CUSTOMER",
    "CHANGED_ON":"2024-02-19",
    "CHANGED_AT":"09:20:46",
    "DT_UUID":"AB54FC360F6F1EDEB3E1052D31091F64",
    "SOURCE_ORIGIN":"0",
    "SRVD_SOURCE_TYPE":"S",
    "ABAP_LANGUAGE_VERSION":"5"
   }
  ]
 },
 {
  "table":"SRVDSRCT",
  "data":
  [
   {
    "SRVDNAME":"ZSD_NFT_T008",
    "VERSION":"A",
    "LANGUAGE":"T",
    "DESCRIPTION":"Masraf dağıtım hesaplama"
   }
  ]
 },
 {
  "table":"SRVDSRC_SRC",
  "data":
  [
   {
    "SRVDNAME":"ZSD_NFT_T008",
    "VERSION":"A",
    "SOURCE":"@EndUserText.label: 'Masraf dağıtım hesaplama'\r\ndefine service ZSD_NFT_T008 {\r\n  expose ZC_NFT_DDL_T008 as T008;\r\n}"
   }
  ]
 },
 {
  "table":"SRVD_RT_ANNOS",
  "data":
  [
   {
    "SRVDNAME":"ZSD_NFT_T008",
    "NAME":"ENDUSERTEXT.LABEL",
    "VALUE":"'Masraf dağıtım hesaplama'"
   }
  ]
 },
 {
  "table":"SRVD_RT_ANNOS_T",
  "data":
  [
   {
    "SRVDNAME":"ZSD_NFT_T008",
    "LANGUAGE":"T",
    "NAME":"ENDUSERTEXT.LABEL",
    "TEXT":"Masraf dağıtım hesaplama"
   }
  ]
 },
 {
  "table":"SRVD_RT_ENTITIES",
  "data":
  [
   {
    "SRVDNAME":"ZSD_NFT_T008",
    "SERVICE":"ZSD_NFT_T008",
    "EXPOSED_ARTIFACT":"ZC_NFT_DDL_T008",
    "EXPOSED_ARTIFACT_TYPE":"E",
    "EXPOSED_ALIAS":"T008",
    "EXPOSED_ALIAS_RAW":"T008",
    "INCL_SERVICE":""
   }
  ]
 },
 {
  "table":"SRVD_RT_HEADER",
  "data":
  [
   {
    "SRVDNAME":"ZSD_NFT_T008",
    "SERVICE":"ZSD_NFT_T008",
    "SERVICE_RAW":"ZSD_NFT_T008",
    "SOURCE_TYPE":"S",
    "DT_UUID":"AB54FC360F6F1EDEB3E1052D31091F64",
    "RT_HASH":"82A70CDDD1F33CADB4CC63D1F1EF5D3939D6D5F5",
    "GEN_VERSION":"0"
   }
  ]
 },
 {
  "table":"TADIR",
  "data":
  [
   {
    "PGMID":"R3TR",
    "OBJECT":"SRVD",
    "OBJ_NAME":"ZSD_NFT_T008",
    "KORRNUM":"",
    "SRCSYSTEM":"...",
    "AUTHOR":"SAP_CUSTOMER",
    "SRCDEP":"",
    "DEVCLASS":"ZNFT_IMPORT0",
    "GENFLAG":"",
    "EDTFLAG":"",
    "CPROJECT":" L",
    "MASTERLANG":"T",
    "VERSID":"",
    "PAKNOCHECK":"",
    "OBJSTABLTY":"",
    "COMPONENT":"",
    "CRELEASE":"",
    "DELFLAG":"",
    "TRANSLTTXT":"",
    "CREATED_ON":"2024-02-19",
    "CHECK_DATE":"2024-02-19",
    "CHECK_CFG":""
   }
  ]
 }
]